README.md
setup.py
apetype/__init__.py
apetype/configs.py
apetype/pipelines.py
apetype/reports.py
apetype/tasks.py
apetype/utils.py
apetype/workers.py
apetype.egg-info/PKG-INFO
apetype.egg-info/SOURCES.txt
apetype.egg-info/dependency_links.txt
apetype.egg-info/not-zip-safe
apetype.egg-info/requires.txt
apetype.egg-info/top_level.txt
apetype/tests/__init__.py
apetype/tests/test_configs.py
apetype/tests/test_tasks.py
apetype/tests/test_workers.py