Metadata-Version: 2.1
Name: apetype
Version: 0.0.8
Summary: Embracing builtin python modules argparse and typing for pipelines
Home-page: https://github.com/dicaso/apetype
Author: Christophe Van Neste
Author-email: info@dicaso.be
License: MIT
Platform: UNKNOWN
Requires-Python: >=3.6
Provides-Extra: documentation
Provides-Extra: reporting
